textgrid_convert_ina/ArgParser.py
textgrid_convert_ina/ParserABC.py
textgrid_convert_ina/__main__.py
textgrid_convert_ina/iotools.py
textgrid_convert_ina/preproctools.py
textgrid_convert_ina/revParser.py
textgrid_convert_ina/sbvParser.py
textgrid_convert_ina/srtParser.py
textgrid_convert_ina/textgridtools.py
textgrid_convert_ina/ttextgrid_convert.py
textgrid_convert_ina-1.1.2.dist-info/METADATA
textgrid_convert_ina-1.1.2.dist-info/WHEEL
textgrid_convert_ina-1.1.2.dist-info/top_level.txt
textgrid_convert_ina-1.1.2.dist-info/RECORD
